MANIFEST.in
README.rst
requirements.txt
setup.cfg
setup.py
Schwa.egg-info/PKG-INFO
Schwa.egg-info/SOURCES.txt
Schwa.egg-info/dependency_links.txt
Schwa.egg-info/entry_points.txt
Schwa.egg-info/requires.txt
Schwa.egg-info/top_level.txt
plyj/__init__.py
plyj/model.py
plyj/parser.py
schwa/__init__.py
schwa/__main__.py
schwa/cli.py
schwa/schwa.py
schwa/version.py
schwa/analysis/__init__.py
schwa/analysis/abstract_analysis.py
schwa/analysis/repository_analytics.py
schwa/analysis/schwa_analysis.py
schwa/extraction/__init__.py
schwa/extraction/abstract_extractor.py
schwa/extraction/git_extractor.py
schwa/learning/__init__.py
schwa/learning/feature_weight_learner.py
schwa/parsing/__init__.py
schwa/parsing/abstract_parser.py
schwa/parsing/java_parser.py
schwa/repository/__init__.py
schwa/repository/file.py
schwa/repository/repository.py
schwa/test/__init__.py
schwa/test/configuration_test.py
schwa/test/feature_weight_learner_test.py
schwa/test/git_extractor_test.py
schwa/test/java_parser_test.py
schwa/test/schwa_analysis_test.py
schwa/web/__init__.py
schwa/web/server.py
schwa/web/static/app.js
schwa/web/static/d3.min.js
schwa/web/static/styles.css
schwa/web/views/index.tpl