Metadata-Version: 1.1
Name: Schwa
Version: 0.1.dev27
Summary: A tool that predicts Software defects from GIT repositories.
Home-page: https://github.com/andrefreitas/schwa
Author: Andre Freitas
Author-email: p.andrefreitas@gmail.com
License: MIT
Keywords: testing,bugs,software
Platform: UNKNOWN
Classifier: Development Status :: 3 - Alpha
Classifier: Intended Audience :: Developers
Classifier: Topic :: Software Development :: Build Tools
Classifier: License :: OSI Approved :: MIT License
Classifier: Programming Language :: Python :: 3
Classifier: Programming Language :: Python :: 3.2
Classifier: Programming Language :: Python :: 3.3
Classifier: Programming Language :: Python :: 3.4
